instagram_analyzer
