Metadata-Version: 2.1
Name: instagram-analyzer
Version: 1.0.3
Summary: Analyzes user's Instagram location geotags to find most frequent locations, countries, cities
Home-page: https://github.com/nejckorasa/instagram-analyzer
Author: Nejc Korasa
Author-email: nejc.korasa@gmail.com
License: Public domain
Download-URL: https://github.com/nejckorasa/instagram-analyzer/archive/master.zip
Keywords: instagram,location,download,media,photos,videos,geocoding
Platform: UNKNOWN
